pygalgen/__init__.py
pygalgen/common/__init__.py
pygalgen/common/utils.py
pygalgen/generator/__init__.py
pygalgen/generator/main.py
pygalgen/generator/pipeline.py
pygalgen/generator/plugin_discovery.py
pygalgen/generator/update.py
pygalgen/generator/common/__init__.py
pygalgen/generator/common/constants.py
pygalgen/generator/common/exceptions.py
pygalgen/generator/common/utils.py
pygalgen/generator/common/xml_utils.py
pygalgen/generator/common/commands/__init__.py
pygalgen/generator/common/commands/command_utils.py
pygalgen/generator/common/macros/__init__.py
pygalgen/generator/common/macros/macros.py
pygalgen/generator/common/params/__init__.py
pygalgen/generator/common/params/argument_parser_conversion.py
pygalgen/generator/common/source_file_parsing/__init__.py
pygalgen/generator/common/source_file_parsing/local_module_parsing.py
pygalgen/generator/common/source_file_parsing/parser_discovery_and_init.py
pygalgen/generator/common/source_file_parsing/parsing_commons.py
pygalgen/generator/common/source_file_parsing/parsing_exceptions.py
pygalgen/generator/common/source_file_parsing/unknown_names_discovery.py
pygalgen/generator/default_plugins/__init__.py
pygalgen/generator/default_plugins/config.yml
pygalgen/generator/default_plugins/data_setup.py
pygalgen/generator/default_plugins/default.py
pygalgen/generator/default_plugins/assets/__init__.py
pygalgen/generator/default_plugins/assets/reserved_var_names.txt
pygalgen/generator/default_plugins/assets/template.xml
pygalgen/generator/default_plugins/strategies/__init__.py
pygalgen/generator/default_plugins/strategies/commands.py
pygalgen/generator/default_plugins/strategies/header.py
pygalgen/generator/default_plugins/strategies/help.py
pygalgen/generator/default_plugins/strategies/outputs.py
pygalgen/generator/default_plugins/strategies/params.py
pygalgen/generator/pluggability/__init__.py
pygalgen/generator/pluggability/data_setup.py
pygalgen/generator/pluggability/plugin.py
pygalgen-0.3.0.dist-info/LICENSE
pygalgen-0.3.0.dist-info/METADATA
pygalgen-0.3.0.dist-info/WHEEL
pygalgen-0.3.0.dist-info/entry_points.txt
pygalgen-0.3.0.dist-info/top_level.txt
pygalgen-0.3.0.dist-info/RECORD
